[
  {
    "type": "event",
    "anonymous": false,
    "name": "AllowancesGranted",
    "inputs": []
  },
  {
    "type": "event",
    "anonymous": false,
    "name": "Approval",
    "inputs": [
      {
        "type": "address",
        "name": "owner",
        "indexed": true
      },
      {
        "type": "address",
        "name": "spender",
        "indexed": true
      },
      {
        "type": "uint256",
        "name": "value",
        "indexed": false
      }
    ]
  },
  {
    "type": "event",
    "anonymous": false,
    "name": "BatchingManagerUpdated",
    "inputs": [
      {
        "type": "address",
        "name": "_batchingManager",
        "indexed": false
      }
    ]
  },
  {
    "type": "event",
    "anonymous": false,
    "name": "Deposit",
    "inputs": [
      {
        "type": "address",
        "name": "caller",
        "indexed": true
      },
      {
        "type": "address",
        "name": "owner",
        "indexed": true
      },
      {
        "type": "uint256",
        "name": "assets",
        "indexed": false
      },
      {
        "type": "uint256",
        "name": "shares",
        "indexed": false
      }
    ]
  },
  {
    "type": "event",
    "anonymous": false,
    "name": "DepositCapUpdated",
    "inputs": [
      {
        "type": "uint256",
        "name": "_newDepositCap",
        "indexed": false
      }
    ]
  },
  {
    "type": "event",
    "anonymous": false,
    "name": "DnGmxSeniorVaultUpdated",
    "inputs": [
      {
        "type": "address",
        "name": "_dnGmxSeniorVault",
        "indexed": false
      }
    ]
  },
  {
    "type": "event",
    "anonymous": false,
    "name": "FeeParamsUpdated",
    "inputs": [
      {
        "type": "uint256",
        "name": "feeBps",
        "indexed": false
      },
      {
        "type": "address",
        "name": "_newFeeRecipient",
        "indexed": false
      }
    ]
  },
  {
    "type": "event",
    "anonymous": false,
    "name": "FeesWithdrawn",
    "inputs": [
      {
        "type": "uint256",
        "name": "feeAmount",
        "indexed": false
      }
    ]
  },
  {
    "type": "event",
    "anonymous": false,
    "name": "Initialized",
    "inputs": [
      {
        "type": "uint8",
        "name": "version",
        "indexed": false
      }
    ]
  },
  {
    "type": "event",
    "anonymous": false,
    "name": "KeeperUpdated",
    "inputs": [
      {
        "type": "address",
        "name": "_newKeeper",
        "indexed": false
      }
    ]
  },
  {
    "type": "event",
    "anonymous": false,
    "name": "OwnershipTransferred",
    "inputs": [
      {
        "type": "address",
        "name": "previousOwner",
        "indexed": true
      },
      {
        "type": "address",
        "name": "newOwner",
        "indexed": true
      }
    ]
  },
  {
    "type": "event",
    "anonymous": false,
    "name": "Paused",
    "inputs": [
      {
        "type": "address",
        "name": "account",
        "indexed": false
      }
    ]
  },
  {
    "type": "event",
    "anonymous": false,
    "name": "RebalanceParamsUpdated",
    "inputs": [
      {
        "type": "uint32",
        "name": "rebalanceTimeThreshold",
        "indexed": true
      },
      {
        "type": "uint16",
        "name": "rebalanceDeltaThreshold",
        "indexed": true
      }
    ]
  },
  {
    "type": "event",
    "anonymous": false,
    "name": "Rebalanced",
    "inputs": []
  },
  {
    "type": "event",
    "anonymous": false,
    "name": "RewardsHarvested",
    "inputs": [
      {
        "type": "uint256",
        "name": "wethHarvested",
        "indexed": false
      },
      {
        "type": "uint256",
        "name": "esGmxStaked",
        "indexed": false
      },
      {
        "type": "uint256",
        "name": "juniorVaultWeth",
        "indexed": false
      },
      {
        "type": "uint256",
        "name": "seniorVaultWeth",
        "indexed": false
      },
      {
        "type": "uint256",
        "name": "juniorVaultGlp",
        "indexed": false
      },
      {
        "type": "uint256",
        "name": "seniorVaultAUsdc",
        "indexed": false
      }
    ]
  },
  {
    "type": "event",
    "anonymous": false,
    "name": "Transfer",
    "inputs": [
      {
        "type": "address",
        "name": "from",
        "indexed": true
      },
      {
        "type": "address",
        "name": "to",
        "indexed": true
      },
      {
        "type": "uint256",
        "name": "value",
        "indexed": false
      }
    ]
  },
  {
    "type": "event",
    "anonymous": false,
    "name": "Unpaused",
    "inputs": [
      {
        "type": "address",
        "name": "account",
        "indexed": false
      }
    ]
  },
  {
    "type": "event",
    "anonymous": false,
    "name": "Withdraw",
    "inputs": [
      {
        "type": "address",
        "name": "caller",
        "indexed": true
      },
      {
        "type": "address",
        "name": "receiver",
        "indexed": true
      },
      {
        "type": "address",
        "name": "owner",
        "indexed": true
      },
      {
        "type": "uint256",
        "name": "assets",
        "indexed": false
      },
      {
        "type": "uint256",
        "name": "shares",
        "indexed": false
      }
    ]
  },
  {
    "type": "event",
    "anonymous": false,
    "name": "WithdrawFeeUpdated",
    "inputs": [
      {
        "type": "uint256",
        "name": "_withdrawFeeBps",
        "indexed": false
      }
    ]
  },
  {
    "type": "event",
    "anonymous": false,
    "name": "YieldParamsUpdated",
    "inputs": [
      {
        "type": "uint16",
        "name": "slippageThresholdGmx",
        "indexed": false
      },
      {
        "type": "uint240",
        "name": "usdcConversionThreshold",
        "indexed": false
      },
      {
        "type": "uint256",
        "name": "wethConversionThreshold",
        "indexed": false
      },
      {
        "type": "uint256",
        "name": "hedgeUsdcAmountThreshold",
        "indexed": false
      },
      {
        "type": "uint256",
        "name": "hfThreshold",
        "indexed": false
      }
    ]
  },
  {
    "type": "function",
    "name": "allowance",
    "constant": true,
    "stateMutability": "view",
    "payable": false,
    "inputs": [
      {
        "type": "address",
        "name": "owner"
      },
      {
        "type": "address",
        "name": "spender"
      }
    ],
    "outputs": [
      {
        "type": "uint256",
        "name": ""
      }
    ]
  },
  {
    "type": "function",
    "name": "approve",
    "constant": false,
    "payable": false,
    "inputs": [
      {
        "type": "address",
        "name": "spender"
      },
      {
        "type": "uint256",
        "name": "amount"
      }
    ],
    "outputs": [
      {
        "type": "bool",
        "name": ""
      }
    ]
  },
  {
    "type": "function",
    "name": "asset",
    "constant": true,
    "stateMutability": "view",
    "payable": false,
    "inputs": [],
    "outputs": [
      {
        "type": "address",
        "name": ""
      }
    ]
  },
  {
    "type": "function",
    "name": "balanceOf",
    "constant": true,
    "stateMutability": "view",
    "payable": false,
    "inputs": [
      {
        "type": "address",
        "name": "account"
      }
    ],
    "outputs": [
      {
        "type": "uint256",
        "name": ""
      }
    ]
  },
  {
    "type": "function",
    "name": "claimVestedGmx",
    "constant": false,
    "payable": false,
    "inputs": [],
    "outputs": []
  },
  {
    "type": "function",
    "name": "convertToAssets",
    "constant": true,
    "stateMutability": "view",
    "payable": false,
    "inputs": [
      {
        "type": "uint256",
        "name": "shares"
      }
    ],
    "outputs": [
      {
        "type": "uint256",
        "name": ""
      }
    ]
  },
  {
    "type": "function",
    "name": "convertToShares",
    "constant": true,
    "stateMutability": "view",
    "payable": false,
    "inputs": [
      {
        "type": "uint256",
        "name": "assets"
      }
    ],
    "outputs": [
      {
        "type": "uint256",
        "name": ""
      }
    ]
  },
  {
    "type": "function",
    "name": "decimals",
    "constant": true,
    "stateMutability": "view",
    "payable": false,
    "inputs": [],
    "outputs": [
      {
        "type": "uint8",
        "name": ""
      }
    ]
  },
  {
    "type": "function",
    "name": "decreaseAllowance",
    "constant": false,
    "payable": false,
    "inputs": [
      {
        "type": "address",
        "name": "spender"
      },
      {
        "type": "uint256",
        "name": "subtractedValue"
      }
    ],
    "outputs": [
      {
        "type": "bool",
        "name": ""
      }
    ]
  },
  {
    "type": "function",
    "name": "deposit",
    "constant": false,
    "payable": false,
    "inputs": [
      {
        "type": "uint256",
        "name": "amount"
      },
      {
        "type": "address",
        "name": "to"
      }
    ],
    "outputs": [
      {
        "type": "uint256",
        "name": "shares"
      }
    ]
  },
  {
    "type": "function",
    "name": "depositCap",
    "constant": true,
    "stateMutability": "view",
    "payable": false,
    "inputs": [],
    "outputs": [
      {
        "type": "uint256",
        "name": ""
      }
    ]
  },
  {
    "type": "function",
    "name": "dnUsdcDeposited",
    "constant": true,
    "stateMutability": "view",
    "payable": false,
    "inputs": [],
    "outputs": [
      {
        "type": "int256",
        "name": ""
      }
    ]
  },
  {
    "type": "function",
    "name": "getCurrentBorrows",
    "constant": true,
    "stateMutability": "view",
    "payable": false,
    "inputs": [],
    "outputs": [
      {
        "type": "uint256",
        "name": "currentBtcBorrow"
      },
      {
        "type": "uint256",
        "name": "currentEthBorrow"
      }
    ]
  },
  {
    "type": "function",
    "name": "getMarketValue",
    "constant": true,
    "stateMutability": "view",
    "payable": false,
    "inputs": [
      {
        "type": "uint256",
        "name": "assetAmount"
      }
    ],
    "outputs": [
      {
        "type": "uint256",
        "name": "marketValue"
      }
    ]
  },
  {
    "type": "function",
    "name": "getOptimalBorrows",
    "constant": true,
    "stateMutability": "view",
    "payable": false,
    "inputs": [
      {
        "type": "uint256",
        "name": "glpDeposited"
      }
    ],
    "outputs": [
      {
        "type": "uint256",
        "name": "optimalBtcBorrow"
      },
      {
        "type": "uint256",
        "name": "optimalEthBorrow"
      }
    ]
  },
  {
    "type": "function",
    "name": "getPrice",
    "constant": true,
    "stateMutability": "view",
    "payable": false,
    "inputs": [
      {
        "type": "bool",
        "name": "maximize"
      }
    ],
    "outputs": [
      {
        "type": "uint256",
        "name": ""
      }
    ]
  },
  {
    "type": "function",
    "name": "getPriceX128",
    "constant": true,
    "stateMutability": "view",
    "payable": false,
    "inputs": [],
    "outputs": [
      {
        "type": "uint256",
        "name": ""
      }
    ]
  },
  {
    "type": "function",
    "name": "getUsdcBorrowed",
    "constant": true,
    "stateMutability": "view",
    "payable": false,
    "inputs": [],
    "outputs": [
      {
        "type": "uint256",
        "name": "usdcAmount"
      }
    ]
  },
  {
    "type": "function",
    "name": "getVaultMarketValue",
    "constant": true,
    "stateMutability": "view",
    "payable": false,
    "inputs": [],
    "outputs": [
      {
        "type": "int256",
        "name": "vaultMarketValue"
      }
    ]
  },
  {
    "type": "function",
    "name": "grantAllowances",
    "constant": false,
    "payable": false,
    "inputs": [],
    "outputs": []
  },
  {
    "type": "function",
    "name": "harvestFees",
    "constant": false,
    "payable": false,
    "inputs": [],
    "outputs": []
  },
  {
    "type": "function",
    "name": "increaseAllowance",
    "constant": false,
    "payable": false,
    "inputs": [
      {
        "type": "address",
        "name": "spender"
      },
      {
        "type": "uint256",
        "name": "addedValue"
      }
    ],
    "outputs": [
      {
        "type": "bool",
        "name": ""
      }
    ]
  },
  {
    "type": "function",
    "name": "initialize",
    "constant": false,
    "payable": false,
    "inputs": [
      {
        "type": "string",
        "name": "_name"
      },
      {
        "type": "string",
        "name": "_symbol"
      },
      {
        "type": "address",
        "name": "_swapRouter"
      },
      {
        "type": "address",
        "name": "_rewardRouter"
      },
      {
        "type": "tuple",
        "name": "_tokens",
        "components": [
          {
            "type": "address",
            "name": "weth"
          },
          {
            "type": "address",
            "name": "wbtc"
          },
          {
            "type": "address",
            "name": "sGlp"
          },
          {
            "type": "address",
            "name": "usdc"
          }
        ]
      },
      {
        "type": "address",
        "name": "_poolAddressesProvider"
      }
    ],
    "outputs": []
  },
  {
    "type": "function",
    "name": "isValidRebalance",
    "constant": true,
    "stateMutability": "view",
    "payable": false,
    "inputs": [],
    "outputs": [
      {
        "type": "bool",
        "name": ""
      }
    ]
  },
  {
    "type": "function",
    "name": "maxDeposit",
    "constant": true,
    "stateMutability": "view",
    "payable": false,
    "inputs": [
      {
        "type": "address",
        "name": ""
      }
    ],
    "outputs": [
      {
        "type": "uint256",
        "name": ""
      }
    ]
  },
  {
    "type": "function",
    "name": "maxMint",
    "constant": true,
    "stateMutability": "view",
    "payable": false,
    "inputs": [
      {
        "type": "address",
        "name": "receiver"
      }
    ],
    "outputs": [
      {
        "type": "uint256",
        "name": ""
      }
    ]
  },
  {
    "type": "function",
    "name": "maxRedeem",
    "constant": true,
    "stateMutability": "view",
    "payable": false,
    "inputs": [
      {
        "type": "address",
        "name": "owner"
      }
    ],
    "outputs": [
      {
        "type": "uint256",
        "name": ""
      }
    ]
  },
  {
    "type": "function",
    "name": "maxWithdraw",
    "constant": true,
    "stateMutability": "view",
    "payable": false,
    "inputs": [
      {
        "type": "address",
        "name": "owner"
      }
    ],
    "outputs": [
      {
        "type": "uint256",
        "name": ""
      }
    ]
  },
  {
    "type": "function",
    "name": "mint",
    "constant": false,
    "payable": false,
    "inputs": [
      {
        "type": "uint256",
        "name": "shares"
      },
      {
        "type": "address",
        "name": "to"
      }
    ],
    "outputs": [
      {
        "type": "uint256",
        "name": "amount"
      }
    ]
  },
  {
    "type": "function",
    "name": "name",
    "constant": true,
    "stateMutability": "view",
    "payable": false,
    "inputs": [],
    "outputs": [
      {
        "type": "string",
        "name": ""
      }
    ]
  },
  {
    "type": "function",
    "name": "owner",
    "constant": true,
    "stateMutability": "view",
    "payable": false,
    "inputs": [],
    "outputs": [
      {
        "type": "address",
        "name": ""
      }
    ]
  },
  {
    "type": "function",
    "name": "pause",
    "constant": false,
    "payable": false,
    "inputs": [],
    "outputs": []
  },
  {
    "type": "function",
    "name": "paused",
    "constant": true,
    "stateMutability": "view",
    "payable": false,
    "inputs": [],
    "outputs": [
      {
        "type": "bool",
        "name": ""
      }
    ]
  },
  {
    "type": "function",
    "name": "previewDeposit",
    "constant": true,
    "stateMutability": "view",
    "payable": false,
    "inputs": [
      {
        "type": "uint256",
        "name": "assets"
      }
    ],
    "outputs": [
      {
        "type": "uint256",
        "name": ""
      }
    ]
  },
  {
    "type": "function",
    "name": "previewMint",
    "constant": true,
    "stateMutability": "view",
    "payable": false,
    "inputs": [
      {
        "type": "uint256",
        "name": "shares"
      }
    ],
    "outputs": [
      {
        "type": "uint256",
        "name": ""
      }
    ]
  },
  {
    "type": "function",
    "name": "previewRedeem",
    "constant": true,
    "stateMutability": "view",
    "payable": false,
    "inputs": [
      {
        "type": "uint256",
        "name": "shares"
      }
    ],
    "outputs": [
      {
        "type": "uint256",
        "name": ""
      }
    ]
  },
  {
    "type": "function",
    "name": "previewWithdraw",
    "constant": true,
    "stateMutability": "view",
    "payable": false,
    "inputs": [
      {
        "type": "uint256",
        "name": "assets"
      }
    ],
    "outputs": [
      {
        "type": "uint256",
        "name": ""
      }
    ]
  },
  {
    "type": "function",
    "name": "rebalance",
    "constant": false,
    "payable": false,
    "inputs": [],
    "outputs": []
  },
  {
    "type": "function",
    "name": "receiveFlashLoan",
    "constant": false,
    "payable": false,
    "inputs": [
      {
        "type": "address[]",
        "name": "tokens"
      },
      {
        "type": "uint256[]",
        "name": "amounts"
      },
      {
        "type": "uint256[]",
        "name": "feeAmounts"
      },
      {
        "type": "bytes",
        "name": "userData"
      }
    ],
    "outputs": []
  },
  {
    "type": "function",
    "name": "redeem",
    "constant": false,
    "payable": false,
    "inputs": [
      {
        "type": "uint256",
        "name": "shares"
      },
      {
        "type": "address",
        "name": "receiver"
      },
      {
        "type": "address",
        "name": "owner"
      }
    ],
    "outputs": [
      {
        "type": "uint256",
        "name": "assets"
      }
    ]
  },
  {
    "type": "function",
    "name": "renounceOwnership",
    "constant": false,
    "payable": false,
    "inputs": [],
    "outputs": []
  },
  {
    "type": "function",
    "name": "setAdminParams",
    "constant": false,
    "payable": false,
    "inputs": [
      {
        "type": "address",
        "name": "_newKeeper"
      },
      {
        "type": "address",
        "name": "_dnGmxSeniorVault"
      },
      {
        "type": "uint256",
        "name": "_newDepositCap"
      },
      {
        "type": "address",
        "name": "_batchingManager"
      },
      {
        "type": "uint256",
        "name": "_withdrawFeeBps"
      }
    ],
    "outputs": []
  },
  {
    "type": "function",
    "name": "setFeeParams",
    "constant": false,
    "payable": false,
    "inputs": [
      {
        "type": "uint256",
        "name": "_feeBps"
      },
      {
        "type": "address",
        "name": "_feeRecipient"
      }
    ],
    "outputs": []
  },
  {
    "type": "function",
    "name": "setHedgeParams",
    "constant": false,
    "payable": false,
    "inputs": [
      {
        "type": "address",
        "name": "_vault"
      },
      {
        "type": "address",
        "name": "_swapRouter"
      },
      {
        "type": "uint256",
        "name": "_targetHealthFactor"
      },
      {
        "type": "address",
        "name": "_aaveRewardsController"
      }
    ],
    "outputs": []
  },
  {
    "type": "function",
    "name": "setRebalanceParams",
    "constant": false,
    "payable": false,
    "inputs": [
      {
        "type": "uint32",
        "name": "_rebalanceTimeThreshold"
      },
      {
        "type": "uint16",
        "name": "_rebalanceDeltaThreshold"
      }
    ],
    "outputs": []
  },
  {
    "type": "function",
    "name": "setThresholds",
    "constant": false,
    "payable": false,
    "inputs": [
      {
        "type": "uint16",
        "name": "_slippageThresholdSwap"
      },
      {
        "type": "uint16",
        "name": "_slippageThresholdGmx"
      },
      {
        "type": "uint208",
        "name": "_usdcConversionThreshold"
      },
      {
        "type": "uint256",
        "name": "_hfThreshold"
      },
      {
        "type": "uint256",
        "name": "_wethConversionThreshold"
      },
      {
        "type": "uint256",
        "name": "_hedgeUsdcAmountThreshold"
      }
    ],
    "outputs": []
  },
  {
    "type": "function",
    "name": "stopVestAndStakeEsGmx",
    "constant": false,
    "payable": false,
    "inputs": [],
    "outputs": []
  },
  {
    "type": "function",
    "name": "symbol",
    "constant": true,
    "stateMutability": "view",
    "payable": false,
    "inputs": [],
    "outputs": [
      {
        "type": "string",
        "name": ""
      }
    ]
  },
  {
    "type": "function",
    "name": "totalAssets",
    "constant": true,
    "stateMutability": "view",
    "payable": false,
    "inputs": [],
    "outputs": [
      {
        "type": "uint256",
        "name": ""
      }
    ]
  },
  {
    "type": "function",
    "name": "totalSupply",
    "constant": true,
    "stateMutability": "view",
    "payable": false,
    "inputs": [],
    "outputs": [
      {
        "type": "uint256",
        "name": ""
      }
    ]
  },
  {
    "type": "function",
    "name": "transfer",
    "constant": false,
    "payable": false,
    "inputs": [
      {
        "type": "address",
        "name": "to"
      },
      {
        "type": "uint256",
        "name": "amount"
      }
    ],
    "outputs": [
      {
        "type": "bool",
        "name": ""
      }
    ]
  },
  {
    "type": "function",
    "name": "transferFrom",
    "constant": false,
    "payable": false,
    "inputs": [
      {
        "type": "address",
        "name": "from"
      },
      {
        "type": "address",
        "name": "to"
      },
      {
        "type": "uint256",
        "name": "amount"
      }
    ],
    "outputs": [
      {
        "type": "bool",
        "name": ""
      }
    ]
  },
  {
    "type": "function",
    "name": "transferOwnership",
    "constant": false,
    "payable": false,
    "inputs": [
      {
        "type": "address",
        "name": "newOwner"
      }
    ],
    "outputs": []
  },
  {
    "type": "function",
    "name": "unpause",
    "constant": false,
    "payable": false,
    "inputs": [],
    "outputs": []
  },
  {
    "type": "function",
    "name": "unstakeAndVestEsGmx",
    "constant": false,
    "payable": false,
    "inputs": [],
    "outputs": []
  },
  {
    "type": "function",
    "name": "withdraw",
    "constant": false,
    "payable": false,
    "inputs": [
      {
        "type": "uint256",
        "name": "assets"
      },
      {
        "type": "address",
        "name": "receiver"
      },
      {
        "type": "address",
        "name": "owner"
      }
    ],
    "outputs": [
      {
        "type": "uint256",
        "name": "shares"
      }
    ]
  },
  {
    "type": "function",
    "name": "withdrawFees",
    "constant": false,
    "payable": false,
    "inputs": [],
    "outputs": []
  }
]
